blackbirdcoop/.DS_Store
blackbirdcoop/1.0.9
blackbirdcoop/__init__.py
blackbirdcoop/blackbirdout.fasta
blackbirdcoop/codonChoice.py
blackbirdcoop/codonOp.py
blackbirdcoop/codonUsage.py
blackbirdcoop/fastAreader.py
blackbirdcoop/stealthHits.py
blackbirdcoop/stealthParser.py
blackbirdcoop/tsvReader.py
blackbirdcoop-1.1.0.dist-info/LICENSE
blackbirdcoop-1.1.0.dist-info/METADATA
blackbirdcoop-1.1.0.dist-info/WHEEL
blackbirdcoop-1.1.0.dist-info/entry_points.txt
blackbirdcoop-1.1.0.dist-info/RECORD
