Metadata-Version: 2.1
Name: blackbirdCoOp
Version: 1.1.0
Summary: A Stealth-based pipeline that optimizes inserts for cyanobacterial transformations in non-model organisms.
Home-page: https://gitlab.igem.org/2024/software-tools/ucsc
License: MIT
Author: Vibhitha Nandakumar
Author-email: vinandak@ucsc.edu
Requires-Python: >=3.9,<3.13
Classifier: License :: OSI Approved :: MIT License
Classifier: Programming Language :: Python :: 3
Classifier: Programming Language :: Python :: 3.9
Classifier: Programming Language :: Python :: 3.10
Classifier: Programming Language :: Python :: 3.11
Classifier: Programming Language :: Python :: 3.12
Project-URL: Repository, https://gitlab.igem.org/2024/software-tools/ucsc
